Products.urban-2.5.0.dev25-py3.13-nspkg.pth
Products/urban/Applicant.py
Products/urban/Article127.py
Products/urban/City.py
Products/urban/Claimant.py
Products/urban/ComplementaryDelayTerm.py
Products/urban/ConfigTest.py
Products/urban/Contact.py
Products/urban/Corporation.py
Products/urban/Couple.py
Products/urban/EnvironmentRubricTerm.py
Products/urban/FolderManager.py
Products/urban/LicenceConfig.py
Products/urban/Locality.py
Products/urban/MiscDemand.py
Products/urban/OpinionRequestEventType.py
Products/urban/OrganisationTerm.py
Products/urban/ParcellingTerm.py
Products/urban/PcaTerm.py
Products/urban/PersonTitleTerm.py
Products/urban/PortionOut.py
Products/urban/PreliminaryNotice.py
Products/urban/Recipient.py
Products/urban/RecipientCadastre.py
Products/urban/RoadDecree.py
Products/urban/SpecificFeatureTerm.py
Products/urban/Street.py
Products/urban/UrbanConfigurationValue.py
Products/urban/UrbanDelay.py
Products/urban/UrbanDoc.py
Products/urban/UrbanEvent.py
Products/urban/UrbanEventOpinionRequest.py
Products/urban/UrbanEventType.py
Products/urban/UrbanTool.py
Products/urban/UrbanVocabularyTerm.py
Products/urban/__init__.py
Products/urban/config.py
Products/urban/configure.zcml
Products/urban/exportimport.py
Products/urban/factory.py
Products/urban/generatedsubscribers.zcml
Products/urban/grok.zcml
Products/urban/index.zcml
Products/urban/indexes.py
Products/urban/interfaces.py
Products/urban/mklocales.sh
Products/urban/monkey.py
Products/urban/overrides.zcml
Products/urban/permissions.zcml
Products/urban/profiles.zcml
Products/urban/refresh.txt
Products/urban/setuphandlers.py
Products/urban/subscribers.py
Products/urban/templates.py
Products/urban/testing.py
Products/urban/testing.zcml
Products/urban/tool.gif
Products/urban/utils.py
Products/urban/vocabularies.py
Products/urban/vocabulary.zcml
Products/urban/wfsubscribers.py
Products/urban/Extensions/__init__.py
Products/urban/Extensions/architects.txt
Products/urban/Extensions/check_double_streets.py
products_urban-2.5.0.dev25.dist-info/METADATA
products_urban-2.5.0.dev25.dist-info/WHEEL
products_urban-2.5.0.dev25.dist-info/entry_points.txt
products_urban-2.5.0.dev25.dist-info/namespace_packages.txt
products_urban-2.5.0.dev25.dist-info/top_level.txt
products_urban-2.5.0.dev25.dist-info/RECORD
