Metadata-Version: 2.4
Name: Products.urban
Version: 2.5.0.dev25
Summary: Urban Certificate Management
Home-page: http://www.communesplone.org/les-outils/applications-metier/gestion-des-permis-durbanisme
Author: Simon Delcourt
Author-email: simon.delcourt@imio.be
License: GPL
Keywords: Urban IMIO
Classifier: License :: OSI Approved :: GNU General Public License v2 (GPLv2)
Classifier: Programming Language :: Python
Classifier: Programming Language :: Python :: 2.7
Requires-Dist: archetypes.referencebrowserwidget
Requires-Dist: collective.ckeditor
Requires-Dist: collective.datagridcolumns
Requires-Dist: collective.delaycalculator
Requires-Dist: collective.documentgenerator
Requires-Dist: collective.externaleditor
Requires-Dist: collective.faceted.datewidget
Requires-Dist: collective.fingerpointing
Requires-Dist: collective.fontawesome
Requires-Dist: collective.iconifieddocumentactions
Requires-Dist: collective.js.jqueryui
Requires-Dist: collective.messagesviewlet
Requires-Dist: collective.wfadaptations
Requires-Dist: collective.z3cform.datagridfield>=0.15
Requires-Dist: collective.archetypes.select2
Requires-Dist: five.grok
Requires-Dist: grokcore.component
Requires-Dist: imio.actionspanel
Requires-Dist: imio.dashboard
Requires-Dist: imio.pm.locales
Requires-Dist: imio.pm.wsclient
Requires-Dist: imio.restapi
Requires-Dist: imio.schedule
Requires-Dist: imio.ws.register
Requires-Dist: Pillow
Requires-Dist: Plone
Requires-Dist: Products.CMFPlacefulWorkflow
Requires-Dist: Products.ContentTypeValidator
Requires-Dist: Products.CPUtils
Requires-Dist: Products.DataGridField
Requires-Dist: Products.MasterSelectWidget
Requires-Dist: Products.PasswordStrength
Requires-Dist: plone.api
Requires-Dist: plone.app.referenceintegrity
Requires-Dist: plone.namedfile
Requires-Dist: plone.z3ctable
Requires-Dist: plonetheme.imioapps
Requires-Dist: Products.cron4plone
Requires-Dist: psycopg2
Requires-Dist: python-dateutil
Requires-Dist: python-Levenshtein
Requires-Dist: requests
Requires-Dist: setuptools
Requires-Dist: Sphinx
Requires-Dist: SQLAlchemy
Requires-Dist: testfixtures
Requires-Dist: zope.app.container
Requires-Dist: zope.sqlalchemy
Requires-Dist: urban.restapi
Requires-Dist: urban.vocabulary
Requires-Dist: urban.schedule
Requires-Dist: urban.events
Requires-Dist: python-dateutil
Provides-Extra: test
Requires-Dist: unittest2; extra == "test"
Requires-Dist: zope.testing; extra == "test"
Requires-Dist: plone.testing; extra == "test"
Requires-Dist: testfixtures; extra == "test"
Requires-Dist: plone.formwidget.datetime; extra == "test"
Requires-Dist: plone.app.testing; extra == "test"
Requires-Dist: plone.app.robotframework[debug,test]; extra == "test"
Requires-Dist: ipdb; extra == "test"
Provides-Extra: templates
Requires-Dist: Genshi; extra == "templates"
Dynamic: author
Dynamic: author-email
Dynamic: classifier
Dynamic: description
Dynamic: home-page
Dynamic: keywords
Dynamic: license
Dynamic: provides-extra
Dynamic: requires-dist
Dynamic: summary
